greptimedb_mcp_server/__init__.py
greptimedb_mcp_server/config.py
greptimedb_mcp_server/server.py
greptimedb_mcp_server/utils.py
greptimedb_mcp_server/templates/metrics_analysis/config.yaml
greptimedb_mcp_server/templates/metrics_analysis/template.md
greptimedb_mcp_server/templates/table_operation/config.yaml
greptimedb_mcp_server/templates/table_operation/template.md
iflow_mcp_greptimedb_mcp_server-0.2.2.dist-info/METADATA
iflow_mcp_greptimedb_mcp_server-0.2.2.dist-info/WHEEL
iflow_mcp_greptimedb_mcp_server-0.2.2.dist-info/entry_points.txt
iflow_mcp_greptimedb_mcp_server-0.2.2.dist-info/licenses/LICENSE.md
iflow_mcp_greptimedb_mcp_server-0.2.2.dist-info/RECORD
